LICENSE.txt
MANIFEST.in
README.rst
setup.py
alittlebox/__init__.py
alittlebox/admin.py
alittlebox/apps.py
alittlebox/filtersets.py
alittlebox/models.py
alittlebox/routers.py
alittlebox/serializers.py
alittlebox/tests.py
alittlebox/views.py
alittlebox/viewsets.py
alittlebox.egg-info/PKG-INFO
alittlebox.egg-info/SOURCES.txt
alittlebox.egg-info/dependency_links.txt
alittlebox.egg-info/top_level.txt